{"Year": ["2008\u201309", "2009\u201310", "2009\u201310", "2010\u201311", "2011\u201312", "2012\u201313", "2013\u201314", "2013\u201314", "2014\u201315", "Career\n"], "Team": ["Charlotte", "Golden State", "Washington", "Washington", "Washington", "Washington", "Atlanta", "Chicago", "Detroit", "\n"], "GP": ["33", "10", "8", "52", "17", "41", "53", "6", "23", "243"], "GS": ["1", "2", "0", "1", "2", "3", "6", "0", "0", "15"], "MPG": ["8.1", "27.6", "14.3", "10.4", "23.0", "16.9", "15.5", "8.0", "8.6", "13.8"], "FG": [".364", ".364", ".375", ".390", ".440", ".381", ".414", ".625", ".283", ".392"], "threeP": [".303", ".323", ".389", ".394", ".387", ".397", ".384", ".600", ".182", ".372"], "FT": [".800", ".762", ".889", ".700", ".579", ".714", ".754", ".500", ".000", ".729"], "RPG": ["1.0", "4.7", "2.6", "1.4", "3.4", "2.4", "2.0", ".8", ".9", "1.9"], "APG": [".4", ".9", ".9", ".3", ".6", ".5", ".6", ".3", ".5", ".5"], "SPG": [".2", ".8", ".4", ".3", ".6", ".5", ".5", ".2", ".1", ".4"], "BPG": [".1", ".0", ".1", ".1", ".1", ".1", ".1", ".0", ".0", ".1"], "PPG": ["2.6\n", "9.0\n", "6.4\n", "4.0\n", "9.3", "6.6\n", "5.9\n", "2.5\n", "1.6\n", "5.1\n"]}