{"Year": ["1962\u201363", "1963\u201364", "1964\u201365", "1965\u201366", "1966\u201367", "1967\u201368", "1968\u201369", "1968\u201369", "1969\u201370", "1970\u201371", "1971\u201372", "1972\u201373", "1973\u201374"], "Team": ["Detroit", "Detroit", "Detroit", "Detroit", "Detroit", "Detroit", "Detroit", "New York", "New York", "New York", "New York", "New York", "New York"], "GP": ["80", "15", "79", "79", "78", "80", "29", "47", "79", "81", "80", "77", "71"], "GS": ["\u2013", "\u2013", "\u2013", "\u2013", "\u2013", "\u2013", "\u2013", "\u2013", "\u2013", "\u2013", "\u2013", "\u2013", "\u2013"], "MPG": ["29.4", "20.3", "35.1", "34.1", "37.1", "39.1", "37.7", "39.4", "33.3", "35.7", "38.4", "36.7", "38.0"], "FG": [".430", ".391", ".425", ".408", ".415", ".442", ".447", ".442", ".451", ".421", ".427", ".435", ".461"], "threeP": ["\u2013", "\u2013", "\u2013", "\u2013", "\u2013", "\u2013", "\u2013", "\u2013", "\u2013", "\u2013", "\u2013", "\u2013", "\u2013"], "FT": [".718", ".581", ".700", ".659", ".705", ".664", ".723", ".682", ".688", ".696", ".728", ".746", ".756"], "RPG": ["8.7", "7.0", "11.1", "11.6", "11.8", "13.5", "12.2", "11.4", "10.0", "11.1", "11.3", "10.2", "10.7"], "APG": ["2.6", "1.5", "3.2", "2.6", "2.8", "2.3", "2.2", "2.7", "2.5", "2.7", "3.6", "3.4", "3.6"], "SPG": ["\u2013", "\u2013", "\u2013", "\u2013", "\u2013", "\u2013", "\u2013", "\u2013", "\u2013", "\u2013", "\u2013", "\u2013", "0.9"], "BPG": ["\u2013", "\u2013", "\u2013", "\u2013", "\u2013", "\u2013", "\u2013", "\u2013", "\u2013", "\u2013", "\u2013", "\u2013", "0.5"], "PPG": ["12.7\n", "8.6\n", "16.7\n", "16.4\n", "18.2", "17.9\n", "16.3\n", "16.4\n", "14.6\n", "15.6\n", "15.4\n", "16.3\n", "18.1\n"]}