{"Year": ["2003\u201304", "2004\u201305", "2005\u201306", "2006\u201307", "2007\u201308", "2007\u201308", "2008\u201309", "2009\u201310", "2009\u201310", "2010\u201311", "2011\u201312"], "Team": ["Denver", "Denver", "Denver", "San Antonio", "San Antonio", "Seattle", "Milwaukee", "Milwaukee", "Philadelphia", "Utah", "Philadelphia"], "GP": ["62", "67", "72", "70", "41", "22", "59", "11", "1", "62", "5"], "GS": ["14", "11", "54", "41", "3", "2", "23", "0", "0", "1", "0"], "MPG": ["14.1", "14.0", "21.9", "19.0", "13.0", "12.7", "16.6", "5.6", "4.0", "9.8", "3.2"], "FG": [".472", ".468", ".532", ".511", ".419", ".341", ".491", ".308", ".500", ".478", ".333"], "threeP": [".000", ".333", ".200", ".000", ".000", ".000", ".250", ".000", ".000", ".000", ".000"], "FT": [".667", ".570", ".662", ".775", ".833", ".462", ".846", "1.000", ".000", ".839", ".000"], "RPG": ["3.3", "3.0", "4.7", "4.8", "3.3", "3.0", "3.9", "1.2", "1.0", "1.9", ".2"], "APG": [".5", ".5", ".7", ".8", ".4", ".4", ".5", ".2", ".0", ".5", ".2"], "SPG": [".6", ".5", ".8", ".4", ".2", ".3", ".6", ".1", ".0", ".3", ".2"], "BPG": [".6", ".6", ".6", ".8", ".3", ".3", ".6", ".0", ".0", ".2", ".2"], "PPG": ["3.5\n", "3.7\n", "4.9\n", "5.0", "3.5\n", "3.0\n", "3.4\n", ".9\n", "2.0\n", "2.2\n", ".4\n"]}