{"Year": ["1981-82", "1982-83", "1983-84", "1984-85", "1985-86", "1986-87", "1987-88", "1987-88", "1988-89", "1989-90", "1990-91", "1991-92", "1992-93", "1993-94"], "Team": ["Phoenix", "Phoenix", "Phoenix", "Phoenix", "Phoenix", "Phoenix", "Phoenix", "Cleveland", "Cleveland", "Cleveland", "Cleveland", "Cleveland", "Cleveland", "Cleveland"], "GP": ["80", "82", "82", "61", "73", "69", "40", "27", "73", "62", "80", "81", "77", "33"], "GS": ["0", "82", "82", "55", "69", "67", "34", "26", "72", "53", "78", "81", "77", "19"], "MPG": ["14.8", "35.5", "35.4", "36.1", "34.0", "37.2", "36.9", "33.6", "34.6", "33.3", "36.6", "35.6", "35.8", "27.5"], "FG": [".521", ".550", ".576", ".587", ".581", ".551", ".531", ".526", ".539", ".511", ".524", ".539", ".549", ".487"], "threeP": [".000", ".333", ".000", ".500", ".000", ".200", ".400", ".000", ".000", "1.000", ".250", ".000", ".000", ".000"], "FT": [".641", ".672", ".707", ".709", ".698", ".773", ".751", ".830", ".799", ".778", ".803", ".822", ".818", ".753"], "RPG": ["3.2", "8.7", "8.3", "8.8", "8.5", "8.7", "9.9", "7.9", "8.0", "8.3", "8.6", "8.3", "8.7", "6.9"], "APG": ["1.0", "2.4", "2.6", "2.6", "3.3", "3.4", "3.1", "3.1", "2.2", "2.6", "3.0", "2.9", "2.9", "1.5"], "SPG": [".5", "1.2", "1.0", "1.4", "1.0", "1.2", "1.1", ".7", ".8", ".9", ".8", "1.0", ".7", ".8"], "BPG": [".9", "2.6", "2.1", "1.7", "1.8", "2.1", "2.4", "2.3", "2.8", "2.0", "2.5", "3.0", "2.6", "1.7"], "PPG": ["6.6", "16.7", "17.7", "19.9", "20.2", "22.5", "21.1", "16.2", "17.2", "16.3", "19.2", "17.0", "16.5", "11.2"], "Name": ["Larry Nance"]}