{"Year": ["2006\u201307", "2012\u201313", "2013\u201314", "2014\u201315", "2015\u201316", "2016\u201317", "2016\u201317", "2017\u201318"], "Team": ["Toronto", "Phoenix", "Phoenix", "Phoenix", "Phoenix", "Phoenix", "Toronto", "Houston"], "GP": ["17", "79", "81", "78", "82", "57", "24", "82"], "GS": ["0", "45", "81", "63", "80", "17", "4", "34"], "MPG": ["4.9", "24.2", "30.7", "30.6", "31.0", "28.5", "25.4", "27.8"], "FG": [".500", ".473", ".431", ".438", ".411", ".415", ".406", ".390"], "threeP": [".000", ".314", ".387", ".345", ".330", ".338", ".400", ".371"], "FT": [".571", ".744", ".776", ".727", ".746", ".792", ".688", ".717"], "RPG": ["1.4", "4.4", "6.5", "6.4", "6.2", "6.0", "5.4", "5.6"], "APG": [".2", "1.4", "1.7", "1.6", "2.2", "1.3", "1.1", ".9"], "SPG": [".1", ".8", "1.4", "1.4", "1.3", "1.5", "1.3", "1.0"], "BPG": [".0", ".2", ".3", ".3", ".2", ".2", ".2", ".3"], "PPG": ["1.8\n", "6.4\n", "9.4", "9.1\n", "8.0\n", "7.0\n", "5.8\n", "6.1\n"]}