{"Year": ["2005-06 Freshman", "2006-07 Sophomore", "2007-08 Junior", "2008-09 Senior"], "Team": ["Pittsburgh Panthers", "Pittsburgh Panthers", "Pittsburgh Panthers", "Pittsburgh Panthers"], "GP": ["33", "37", "37", "36"], "GS": ["3", "2", "37", "36"], "MPG": ["20.4", "17.2", "32.1", "31.8"], "FG": [".521", ".458", ".503", ".502"], "threeP": [".190", ".310", ".383", ".372"], "FT": [".693", ".597", ".690", ".740"], "RPG": ["4.4", "3.0", "6.3", "6.3"], "APG": ["0.8", ".7", "1.2", "1.1"], "SPG": [".7", ".6", "1.1", "1.0"], "BPG": ["0.6", "0.5", "1.1", "0.8"], "PPG": ["7.9", "7.2", "18.1", "19.2"], "Name": ["Sam Young "]}